quotes/__init__.py
quotes/read.py
quotes/spiders.py
quotes/write.py
quotes/assets/albert_einstein.csv
quotes/assets/benjamin_franklin.csv
quotes/assets/emily_carr.csv
quotes/assets/henry_ford.csv
quotes/assets/index.csv
quotes/assets/internet.csv
quotes/assets/mahatma_gandhi.csv
quotes/assets/sets.csv
quotes-0.0.3.dist-info/DESCRIPTION.rst
quotes-0.0.3.dist-info/METADATA
quotes-0.0.3.dist-info/RECORD
quotes-0.0.3.dist-info/WHEEL
quotes-0.0.3.dist-info/metadata.json
quotes-0.0.3.dist-info/top_level.txt
tests/__init__.py
tests/test_read.py
